latex_kelonmyosa.py
latex_kelonmyosa-0.1.0.dist-info/METADATA
latex_kelonmyosa-0.1.0.dist-info/WHEEL
latex_kelonmyosa-0.1.0.dist-info/RECORD
